msk/__init__.py
msk/__main__.py
msk/console_action.py
msk/exceptions.py
msk/global_context.py
msk/lazy.py
msk/repo_action.py
msk/util.py
msk/actions/create.py
msk/actions/create_test.py
msk/actions/submit.py
msk/actions/upgrade.py
msk/actions/upload.py
msk/licenses/Apache-v2.0.txt
msk/licenses/GPL-v3.0.txt
msk/licenses/MIT.txt
msk-0.4.0.dist-info/LICENSE
msk-0.4.0.dist-info/METADATA
msk-0.4.0.dist-info/WHEEL
msk-0.4.0.dist-info/entry_points.txt
msk-0.4.0.dist-info/top_level.txt
msk-0.4.0.dist-info/RECORD
