Metadata-Version: 2.1
Name: msk
Version: 0.4.0
Summary: Mycroft Skills Kit
Home-page: https://github.com/MycroftAI/mycroft-skills-kit
Author: Mycroft AI
Author-email: support@mycroft.ai
License: Apache-2.0
Platform: UNKNOWN
Classifier: Development Status :: 4 - Beta
Classifier: Intended Audience :: Developers
Classifier: License :: OSI Approved :: Apache Software License
Classifier: Programming Language :: Python :: 3.5
Classifier: Programming Language :: Python :: 3.6
Classifier: Programming Language :: Python :: 3.7
Classifier: Programming Language :: Python :: 3.8
Requires-Dist: GitPython (>=3.0.5)
Requires-Dist: colorama
Requires-Dist: msm (~=0.9.0)
Requires-Dist: pygithub
Requires-Dist: requests
